setup.py
redgreen/__init__.py
redgreen/__version__.py
redgreen/directory_change_iterator.py
redgreen/file_change_iterator.py
redgreen/file_status.py
redgreen/sleeper.py
redgreen.egg-info/PKG-INFO
redgreen.egg-info/SOURCES.txt
redgreen.egg-info/dependency_links.txt
redgreen.egg-info/entry_points.txt
redgreen.egg-info/top_level.txt
redgreen/scripts/__init__.py